Workbook

Sheet  DATASET CONTEXT
A1: EXECUTIVE OVERVIEW & DATASET CONTEXT
A2: Field Name | B2: DataType | C2: Description/Business Rule
A3: transaction_id | B3: String/PK | C3: Unique identifier per sales record.
A4: customer_id | B4: String/FK | C4: Unique customer identifier.
A5: transaction_date | B5: Datetime | C5: Timestamp of purchase order execution
A6: region | B6: String | C6: Geographic sales territory (North,South,East,West)
A7: product_category | B7: String | C7: Product line classification.
A8: unit_price/quantity | B8: Numeric | C8: Base unit price and volume ordered
A9: discount_percent | B9: Numeric(0–1) | C9: Discount applied at checkout
A10: customer_signup_date | B10: Datetime | C10: Original account creation

Sheet Task 1
A1: Transaction ID | B1: Customer ID | C1: Tx Date | D1: Region | E1: Category | F1: Unit Price | G1: Qty | H1: Discount Rate | I1: Signup Date | J1: Gross Revenue | K1: Net Revenue | L1: Customer Tag | M1: Discount Amount | N1: Risk Flag
A2: TXN-10001 | B2: CUST-4170 | C2: {=C2:M7311/30/2025} -> 0 | D2: East | E2: Hardware | F2: 341.07 | G2: 9 | H2: 0.25 | I2: 45802 | J2: =F2*G2 -> 3069.63 | K2: =(F2*G2)*(1-H2) -> 2302.2225 | L2: =IF(_xlfn.DAYS(C2,I2)>30,"RETURNING","NEW") -> RETURNING | M2: =(F2*G2)*H2 -> 767.4075 | N2: =_xlfn.XLOOKUP(B2, 'Task 2'!$E:$E,'Task 2'!$I:$I,"High Risk",0) -> High Risk
A3: TXN-10002 | B3: CUST-6088 | C3: 45906 | D3: North | E3: Office Supplies | F3: 31.02 | G3: 1 | H3: 0.2 | I3: 45869 | J3: =F3*G3 -> 31.02 | K3: =(F3*G3)*(1-H3) -> 24.816 | L3: =IF(_xlfn.DAYS(C3,I3)>30,"RETURNING","NEW") -> RETURNING | M3: =(F3*G3)*H3 -> 6.204 | N3: =_xlfn.XLOOKUP(B3, 'Task 2'!$E:$E,'Task 2'!$I:$I,"Good",0) -> Good
A4: TXN-10003 | B4: CUST-7265 | C4: 46008 | D4: North | E4: Hardware | F4: 448.54 | G4: 5 | H4: 0.3 | I4: 45956 | J4: =F4*G4 -> 2242.7 | K4: =(F4*G4)*(1-H4) -> 1569.89 | L4: =IF(_xlfn.DAYS(C4,I4)>30,"RETURNING","NEW") -> RETURNING | M4: =(F4*G4)*H4 -> 672.81 | N4: =_xlfn.XLOOKUP(B4, 'Task 2'!$E:$E,'Task 2'!$I:$I,"Good",0) -> High Risk
A5: TXN-10004 | B5: CUST-4073 | C5: 46022 | D5: South | E5: Furniture | F5: 122.6 | G5: 14 | H5: 0 | I5: 45932 | J5: =F5*G5 -> 1716.4 | K5: =(F5*G5)*(1-H5) -> 1716.4 | L5: =IF(_xlfn.DAYS(C5,I5)>30,"RETURNING","NEW") -> RETURNING | M5: =(F5*G5)*H5 -> 0 | N5: =_xlfn.XLOOKUP(B5, 'Task 2'!$E:$E,'Task 2'!$I:$I,"Good",0) -> Good
A6: TXN-10005 | B6: CUST-8270 | C6: 45946 | D6: North | E6: Software | F6: 114.46 | G6: 1 | H6: 0.05 | I6: 45808 | J6: =F6*G6 -> 114.46 | K6: =(F6*G6)*(1-H6) -> 108.737 | L6: =IF(_xlfn.DAYS(C6,I6)>30,"RETURNING","NEW") -> RETURNING | M6: =(F6*G6)*H6 -> 5.723 | N6: =_xlfn.XLOOKUP(B6, 'Task 2'!$E:$E,'Task 2'!$I:$I,"Good",0) -> Good
A7: TXN-10006 | B7: CUST-4104 | C7: 45884 | D7: South | E7: Office Supplies | F7: 241.33 | G7: 6 | H7: 0.1 | I7: 45879 | J7: =F7*G7 -> 1447.98 | K7: =(F7*G7)*(1-H7) -> 1303.182 | L7: =IF(_xlfn.DAYS(C7,I7)>30,"RETURNING","NEW") -> NEW | M7: =(F7*G7)*H7 -> 144.798 | N7: =_xlfn.XLOOKUP(B7, 'Task 2'!$E:$E,'Task 2'!$I:$I,"Good",0) -> Good
A8: TXN-10007 | B8: CUST-8683 | C8: 45889 | D8: West | E8: Hardware | F8: 53.46 | G8: 11 | H8: 0 | I8: 45813 | J8: =F8*G8 -> 588.06 | K8: =(F8*G8)*(1-H8) -> 588.06 | L8: =IF(_xlfn.DAYS(C8,I8)>30,"RETURNING","NEW") -> RETURNING | M8: =(F8*G8)*H8 -> 0 | N8: =_xlfn.XLOOKUP(B8, 'Task 2'!$E:$E,'Task 2'!$I:$I,"Good",0) -> Good
A9: TXN-10008 | B9: CUST-6977 | C9: 45944 | D9: East | E9: Hardware | F9: 284.83 | G9: 2 | H9: 0.1 | I9: 45915 | J9: =F9*G9 -> 569.66 | K9: =(F9*G9)*(1-H9) -> 512.694 | L9: =IF(_xlfn.DAYS(C9,I9)>30,"RETURNING","NEW") -> NEW | M9: =(F9*G9)*H9 -> 56.966 | N9: =_xlfn.XLOOKUP(B9, 'Task 2'!$E:$E,'Task 2'!$I:$I,"Good",0) -> Good
A10: TXN-10009 | B10: CUST-4840 | C10: 45886 | D10: West | E10: Office Supplies | F10: 167.51 | G10: 2 | H10: 0.05 | I10: 45880 | J10: =F10*G10 -> 335.02 | K10: =(F10*G10)*(1-H10) -> 318.269 | L10: =IF(_xlfn.DAYS(C10,I10)>30,"RETURNING","NEW") -> NEW | M10: =(F10*G10)*H10 -> 16.751 | N10: =_xlfn.XLOOKUP(B10, 'Task 2'!$E:$E,'Task 2'!$I:$I,"Good",0) -> Good
A11: TXN-10010 | B11: CUST-3975 | C11: 45739 | D11: East | E11: Office Supplies | F11: 166.49 | G11: 6 | H11: 0 | I11: 45703 | J11: =F11*G11 -> 998.94 | K11: =(F11*G11)*(1-H11) -> 998.94 | L11: =IF(_xlfn.DAYS(C11,I11)>30,"RETURNING","NEW") -> RETURNING | M11: =(F11*G11)*H11 -> 0 | N11: =_xlfn.XLOOKUP(B11, 'Task 2'!$E:$E,'Task 2'!$I:$I,"Good",0) -> Good
A12: TXN-10011 | B12: CUST-5658 | C12: 45758 | D12: East | E12: Electronics | F12: 428.04 | G12: 4 | H12: 0.05 | I12: 45715 | J12: =F12*G12 -> 1712.16 | K12: =(F12*G12)*(1-H12) -> 1626.552 | L12: =IF(_xlfn.DAYS(C12,I12)>30,"RETURNING","NEW") -> RETURNING | M12: =(F12*G12)*H12 -> 85.608 | N12: =_xlfn.XLOOKUP(B12, 'Task 2'!$E:$E,'Task 2'!$I:$I,"Good",0) -> Good
A13: TXN-10012 | B13: CUST-3931 | C13: 45797 | D13: North | E13: Software | F13: 43.81 | G13: 5 | H13: 0.05 | I13: 45714 | J13: =F13*G13 -> 219.05 | K13: =(F13*G13)*(1-H13) -> 208.0975 | L13: =IF(_xlfn.DAYS(C13,I13)>30,"RETURNING","NEW") -> RETURNING | M13: =(F13*G13)*H13 -> 10.9525 | N13: =_xlfn.XLOOKUP(B13, 'Task 2'!$E:$E,'Task 2'!$I:$I,"Good",0) -> Good
A14: TXN-10013 | B14: CUST-4354 | C14: 45741 | D14: North | E14: Furniture | F14: 267.15 | G14: 11 | H14: 0.1 | I14: 45711 | J14: =F14*G14 -> 2938.65 | K14: =(F14*G14)*(1-H14) -> 2644.785 | L14: =IF(_xlfn.DAYS(C14,I14)>30,"RETURNING","NEW") -> NEW | M14: =(F14*G14)*H14 -> 293.865 | N14: =_xlfn.XLOOKUP(B14, 'Task 2'!$E:$E,'Task 2'!$I:$I,"Good",0) -> Good
... A121: TXN-10120 | B121: CUST-9433 | C121: 45699 | D121: North | E121: Electronics | F121: 397.2 | G121: 3 | H121: 0.15 | I121: 45662 | J121: =F121*G121 -> 1191.6 | K121: =(F121*G121)*(1-H121) -> 1012.86 | L121: =IF(_xlfn.DAYS(C121,I121)>30,"RETURNING","NEW") -> RETURNING | M121: =(F121*G121)*H121 -> 178.74 | N121: =_xlfn.XLOOKUP(B121, 'Task 2'!$E:$E,'Task 2'!$I:$I,"Good",0) -> Good

Sheet Task 2
A1: Product Categories Driving Net Revenue in each Region | F1: Month-over-Month (MoM) revenue growth rates
A4: Region | B4: Net Revenue | F4: Month | G4: Net Revenue | H4: MoM Growth% | I4: Sum of Discount Rate
A5: East | B5: 37818.531 | F5: Jan | G5: 6826.0265 | I5: 0.17129601
A6: Furniture | B6: 17103.714 | F6: Feb | G6: 6716.8165 | H6: -0.015999059 | I6: 0.1257765
A7: Software | B7: 10898.658 | F7: Mar | G7: 21783.846 | H7: 2.2431802 | I7: 0.092607431
A8: Hardware | B8: 9816.1585 | F8: Apr | G8: 18319.991 | H8: -0.15901024 | I8: 0.059932343
A9: North | B9: 33793.961 | F9: May | G9: 4927.512 | H9: -0.73103088 | I9: 0.13548933
A10: Electronics | B10: 15209.92 | F10: Jun | G10: 15980.372 | H10: 2.2430914 | I10: 0.11177175
A11: Furniture | B11: 10546.825 | F11: Jul | G11: 13904.462 | H11: -0.12990373 | I11: 0.11126055
A12: Hardware | B12: 8037.2155 | F12: Aug | G12: 32008.258 | H12: 1.3020134 | I12: 0.19525398
A13: South | B13: 37481.55 | F13: Sep | G13: 21798.34 | H13: -0.31897761 | I13: 0.17323676
A14: Office Supplies | B14: 21021.428 | F14: Oct | G14: 22293.222 | H14: 0.022702737 | I14: 0.12627439
A15: Furniture | B15: 8453.284 | F15: Nov | G15: 6644.884 | H15: -0.70193255 | I15: 0.090209276
A16: Hardware | B16: 8006.838 | F16: Dec | G16: 14421.388 | H16: 1.1702994 | I16: 0.10595696
A17: West | B17: 40803.658
A18: Electronics | B18: 16299.364
A19: Software | B19: 12848.057
A20: Hardware | B20: 11656.237
E27: Row Labels | F27: Sum of Discount Amount | G27: Sum of Gross Revenue | H27: Sum of Discount Rate | I27: Risk Flag
E28: CUST-6463 | F28: 491.07 | G28: 1636.9 | H28: 0.3 | I28: =IF(H28>0.25,"High Risk","Good") -> High Risk
E29: CUST-7265 | F29: 672.81 | G29: 2242.7 | H29: 0.3 | I29: =IF(H29>0.25,"High Risk","Good") -> High Risk
E30: CUST-6592 | F30: 244.05 | G30: 813.5 | H30: 0.3 | I30: =IF(H30>0.25,"High Risk","Good") -> High Risk
E31: CUST-2028 | F31: 182.439 | G31: 608.13 | H31: 0.3 | I31: =IF(H31>0.25,"High Risk","Good") -> High Risk
E32: CUST-8777 | F32: 942.84 | G32: 3142.8 | H32: 0.3 | I32: =IF(H32>0.25,"High Risk","Good") -> High Risk
E33: CUST-3047 | F33: 278.184 | G33: 927.28 | H33: 0.3 | I33: =IF(H33>0.25,"High Risk","Good") -> High Risk
E34: CUST-6530 | F34: 1109.7 | G34: 3699 | H34: 0.3 | I34: =IF(H34>0.25,"High Risk","Good") -> High Risk
E35: CUST-3693 | F35: 223.242 | G35: 744.14 | H35: 0.3 | I35: =IF(H35>0.25,"High Risk","Good") -> High Risk
E36: CUST-6892 | F36: 112.32 | G36: 374.4 | H36: 0.3 | I36: =IF(H36>0.25,"High Risk","Good") -> High Risk
E37: CUST-3747 | F37: 329.784 | G37: 1099.28 | H37: 0.3 | I37: =IF(H37>0.25,"High Risk","Good") -> High Risk
E38: CUST-7668 | F38: 1188.972 | G38: 3963.24 | H38: 0.3 | I38: =IF(H38>0.25,"High Risk","Good") -> High Risk
E39: CUST-3790 | F39: 1463.532 | G39: 4878.44 | H39: 0.3 | I39: =IF(H39>0.25,"High Risk","Good") -> High Risk
... E41: CUST-6249 | F41: 538.035 | G41: 1793.45 | H41: 0.3 | I41: =IF(H41>0.25,"High Risk","Good") -> High Risk
